mobile_money/__init__.py
mobile_money/flutterwave/__init__.py
mobile_money/flutterwave/charge.py
mobile_money/flutterwave/transfer.py
mobile_money/momo/__init__.py
mobile_money/momo/collections.py
mobile_money/momo/disbursments.py
mobile_money/momo/errors.py
mobile_money/momo/sandbox.py
mobile_money/yo/__init__.py
mobile_money/yo/balance.py
mobile_money/yo/constants.py
mobile_money/yo/deposit.py
mobile_money/yo/status.py
mobile_money/yo/withdraw.py
ugmobilemoney-0.1.0.dist-info/LICENSE
ugmobilemoney-0.1.0.dist-info/METADATA
ugmobilemoney-0.1.0.dist-info/WHEEL
ugmobilemoney-0.1.0.dist-info/top_level.txt
ugmobilemoney-0.1.0.dist-info/RECORD
