Metadata-Version: 2.1
Name: ugmobilemoney
Version: 0.1.0
Summary: Carry out Mobile Money Collections and Disbursements from various providers in Uganda
Home-page: https://github.com/open-ug/ugmobilemoney-py
Author: Beingana Jim Junior
Author-email: jimjunior854@gmail.com
License: MIT
Keywords: mobilemoney,uganda,africa,airtel,python,payments,collections,disbursements,mtn
Classifier: Intended Audience :: Developers
Classifier: License :: OSI Approved :: MIT License
Classifier: Operating System :: OS Independent
Classifier: Programming Language :: Python
Classifier: Programming Language :: Python :: 3
Classifier: Topic :: Internet :: WWW/HTTP
Classifier: Topic :: Internet :: WWW/HTTP :: Dynamic Content
Requires-Python: >=3.6
License-File: LICENSE
Requires-Dist: httpx >=0.21.0
Requires-Dist: xmltodict >=0.13.0
Requires-Dist: pycryptodome >=3.20.0
